dformkit/__init__.py
dformkit/check_forms_import.py
dformkit/generate_form.py
dformkit/template_creator.py
dformkit/view_url_manager.py
dformkit/management/commands/__init__.py
dformkit/management/commands/dformkit.py
dformkit-0.1.2.dist-info/LICENSE
dformkit-0.1.2.dist-info/METADATA
dformkit-0.1.2.dist-info/WHEEL
dformkit-0.1.2.dist-info/entry_points.txt
dformkit-0.1.2.dist-info/top_level.txt
dformkit-0.1.2.dist-info/RECORD
