Metadata-Version: 2.2
Name: dformkit
Version: 0.1.2
Summary: A Django library for generating dynamic forms, views, and templates.
Author: Abdulrahman Radan
Author-email: abdulrahmanraadan@gmail.com
License: MIT
Project-URL: Author, https://github.com/abdulrahmanRadan
Project-URL: Homepage, https://github.com/abdulrahmanRadan/dformkit
Project-URL: Bug Tracker, https://github.com/abdulrahmanRadan/dformkit/issues
Project-URL: Source Code, https://github.com/abdulrahmanRadan/dformkit
Project-URL: Documentation, https://github.com/abdulrahmanRadan/dformkit#readme
Keywords: django,dynamic forms,django forms,form generation,web development,dynamic templates,dformkit,pip install dformkit,dformkit install
Platform: Linux
Platform: Windows
Platform: MacOS
Classifier: License :: OSI Approved :: MIT License
Classifier: Operating System :: OS Independent
Classifier: Programming Language :: Python :: 3
Classifier: Programming Language :: Python :: 3.7
Classifier: Programming Language :: Python :: 3.8
Classifier: Programming Language :: Python :: 3.9
Classifier: Framework :: Django
Classifier: Topic :: Software Development :: Libraries
Requires-Python: >=3.6
License-File: LICENSE
Requires-Dist: Django>=3.0
